{
  "animation_count": 0,
  "armature_count": 0,
  "edge_count": 3615,
  "file_identifier": "https://github.com/zhizi-moyu/for_modify_stl/blob/main/output.stl",
  "file_size": 410311,
  "lamp_count": 1,
  "linked_files": [],
  "material_count": 0,
  "mesh_count": 1,
  "metadata": {
    "github_organization": "zhizi-moyu",
    "github_repo": "for_modify_stl"
  },
  "missing_textures": {
    "count": 0,
    "file_path_to_color": {},
    "files": []
  },
  "object_count": 4,
  "poly_count": 2410,
  "random_color": [
    0.8,
    0.8,
    0.8,
    1
  ],
  "save_uid": "output.stl",
  "scene_size": {
    "bbox_max": [
      20.0,
      19.890399932861328,
      37.5
    ],
    "bbox_min": [
      -20.0,
      -19.890399932861328,
      -40.0
    ]
  },
  "sha256": "2207da55520a7058e55d8c55b2b27d7dc8084ba73a889aa936ce3ec350fc0925",
  "shape_key_count": 0,
  "vert_count": 1206
}